Metadata-Version: 2.1
Name: censorify
Version: 0.0.3
Summary: word filter
Author: r4isy
Author-email: r4isydev@gmail.com
